faye/__init__.py
faye/client.py
faye/exceptions.py
faye/extensions.py
faye/protocol/__init__.py
faye/protocol/bayeux.py
faye/protocol/message.py
faye/transport/__init__.py
faye/transport/base.py
faye/transport/http.py
faye/transport/websocket.py
pyfaye-0.1.0.dist-info/entry_points.txt
pyfaye-0.1.0.dist-info/LICENSE
pyfaye-0.1.0.dist-info/METADATA
pyfaye-0.1.0.dist-info/WHEEL
pyfaye-0.1.0.dist-info/RECORD
