Metadata-Version: 2.3
Name: pyfaye
Version: 0.1.0
Summary: Python client for Faye pub/sub protocol
License: MIT
Keywords: faye,websocket,pubsub,realtime,bayeux
Author: Mike Whobrey
Author-email: mwhobrey88@gmail.com
Requires-Python: >=3.10,<4.0
Classifier: Development Status :: 4 - Beta
Classifier: Framework :: AsyncIO
Classifier: Intended Audience :: Developers
Classifier: License :: OSI Approved :: MIT License
Classifier: Programming Language :: Python :: 3
Classifier: Programming Language :: Python :: 3.10
Classifier: Programming Language :: Python :: 3.11
Classifier: Programming Language :: Python :: 3.12
Classifier: Programming Language :: Python :: 3.13
Classifier: Topic :: Internet :: WWW/HTTP :: Dynamic Content
Classifier: Topic :: Software Development :: Libraries :: Python Modules
Requires-Dist: aiohttp (>=3.9.1,<4.0.0)
Requires-Dist: backoff (>=2.2.1,<3.0.0)
Requires-Dist: typing-extensions (>=4.9.0,<5.0.0)
Requires-Dist: websockets (>=12.0,<13.0)
Project-URL: Homepage, https://mikewhob.com/pyfaye
Project-URL: Repository, https://github.com/mwhobrey/pyfaye
